fi_fsa-0.3.17.dist-info/METADATA
fi_fsa-0.3.17.dist-info/WHEEL
fi_fsa-0.3.17.dist-info/entry_points.txt
fi_fsa/__init__.py
fi_fsa/v1/fi_config_v1.py
fi_fsa/v1/fi_fsa_predefine_v1.py
fi_fsa/v1/fi_fsa_v1.py
fi_fsa/v1/fi_logger_v1.py
fi_fsa/v2/fi_config_v2.py
fi_fsa/v2/fi_fsa_predefine_v2.py
fi_fsa/v2/fi_fsa_v2.py
fi_fsa/v2/fi_logger_v2.py
fi_fsa-0.3.17.dist-info/RECORD
