Metadata-Version: 2.1
Name: fi_fsa
Version: 0.3.17
Summary: Fourier Intelligence Actuator SDK for Python.
Author-Email: Honglu Wang <honglu.wang@fftai.com>, Huigang Wang <huigang.wang@fftai.com>
License: MIT
Requires-Python: >=3.10
